taskmanager/__init__.py
taskmanager/__main__.py
taskmanager/admin.py
taskmanager/conftest.py
taskmanager/control.py
taskmanager/exceptions.py
taskmanager/fields.py
taskmanager/models.py
taskmanager/views.py
taskmanager/api/__init__.py
taskmanager/api/health.py
taskmanager/api/v1/__init__.py
taskmanager/api/v1/base.py
taskmanager/api/v1/group.py
taskmanager/api/v1/lock.py
taskmanager/api/v1/meta.py
taskmanager/api/v1/role.py
taskmanager/api/v1/tag.py
taskmanager/api/v1/task.py
taskmanager/api/v1/task_template.py
taskmanager/api/v1/taskgroup.py
taskmanager/api/v1/user.py
taskmanager/auth/__init__.py
taskmanager/auth/forms.py
taskmanager/auth/models.py
taskmanager/callbacks/__init__.py
taskmanager/callbacks/celery_backend.py
taskmanager/callbacks/redis_queue.py
taskmanager/static/android-chrome-512x512.png
taskmanager/static/apple-touch-icon.png
taskmanager/static/browserconfig.xml
taskmanager/static/code.css
taskmanager/static/favicon-16x16.png
taskmanager/static/favicon-32x32.png
taskmanager/static/favicon.ico
taskmanager/static/mstile-144x144.png
taskmanager/static/mstile-150x150.png
taskmanager/static/mstile-310x150.png
taskmanager/static/mstile-310x310.png
taskmanager/static/mstile-70x70.png
taskmanager/static/safari-pinned-tab.svg
taskmanager/static/site.webmanifest
taskmanager/static/style.css
taskmanager/static/img/benjamin_franklin.jpg
taskmanager/static/img/logo.png
taskmanager/static/img/logo.svg
taskmanager/static/img/logo_trans.svg
taskmanager/static/img/van_gogh_wheatfield_with_crows.jpg
taskmanager/static/js/forge.min.js
taskmanager/static/js/misc_jquery.js
taskmanager/templates/_macros.html
taskmanager/templates/base.html
taskmanager/templates/base_email.html
taskmanager/templates/generic_email.html
taskmanager/templates/group.html
taskmanager/templates/groups.html
taskmanager/templates/index.html
taskmanager/templates/mail.html
taskmanager/templates/mail_sent.html
taskmanager/templates/tag.html
taskmanager/templates/tags.html
task_manager-6.5.0.dist-info/LICENSE
task_manager-6.5.0.dist-info/METADATA
task_manager-6.5.0.dist-info/WHEEL
task_manager-6.5.0.dist-info/entry_points.txt
task_manager-6.5.0.dist-info/top_level.txt
task_manager-6.5.0.dist-info/RECORD
