Metadata-Version: 2.1
Name: task-manager
Version: 6.5.0
Summary: The Task Manager is a server that tracks and dispenses tasks for clients to perform.
Home-page: https://gitlab.com/radiology/infrastructure/task-manager
Author: H.C. Achterberg, M. Koek, A. Versteeg, H. Vrooman
Author-email: h.achterberg@erasmusmc.nl, m.koek@erasmusmc.nl, a.versteeg@erasmusmc.nl, h.vrooman@erasmusmc.nl
License: Apache 2.0
Classifier: Development Status :: 5 - Production/Stable
Classifier: Intended Audience :: Developers
Classifier: Intended Audience :: Science/Research
Classifier: Intended Audience :: Healthcare Industry
Classifier: Intended Audience :: Information Technology
Classifier: Intended Audience :: Education
Classifier: License :: OSI Approved :: Apache Software License
Classifier: Natural Language :: English
Classifier: Operating System :: OS Independent
Classifier: Programming Language :: Python :: 3.7
Classifier: Programming Language :: Python :: 3.8
Classifier: Programming Language :: Python :: 3.9
Classifier: Programming Language :: Python :: 3.10
Classifier: Programming Language :: Python :: 3 :: Only
Classifier: Topic :: Scientific/Engineering :: Information Analysis
Classifier: Topic :: System :: Logging
Classifier: Topic :: Utilities
Requires-Python: >=3.7,
License-File: LICENSE
Requires-Dist: alembic ==1.7.7
Requires-Dist: bcrypt ==3.2.0
Requires-Dist: bleach ==4.1.0
Requires-Dist: email-validator ==1.1.3
Requires-Dist: Flask ==2.0.3
Requires-Dist: Flask-BabelEx ==0.9.4
Requires-Dist: Flask-Admin ==1.6.0
Requires-Dist: Flask-Login ==0.5.0
Requires-Dist: Flask-Mail ==0.9.1
Requires-Dist: Flask-Migrate ==3.1.0
Requires-Dist: flask-restx ==0.5.1
Requires-Dist: Flask-Script ==2.0.6
Requires-Dist: Flask-Security-Too ==4.1.3
Requires-Dist: flask-shell-ipython ==0.4.1
Requires-Dist: Flask-SQLAlchemy ==2.5.1
Requires-Dist: Flask-WTF ==1.0.0
Requires-Dist: idna ==3.3
Requires-Dist: python-dotenv ==0.19.2
Requires-Dist: PyMySQL ==1.0.2
Requires-Dist: PyYAML ==6.0.1
Requires-Dist: requests ==2.27.1
Requires-Dist: SQLAlchemy ==1.4.32
Requires-Dist: Werkzeug ==2.0.3
Requires-Dist: WTForms ==2.3.3
